{ "frames": [
   {
    "filename": "particle-heart 0.aseprite",
    "frame": { "x": 0, "y": 0, "w": 8, "h": 8 },
    "rotated": false,
    "trimmed": false,
    "spriteSourceSize": { "x": 0, "y": 0, "w": 8, "h": 8 },
    "sourceSize": { "w": 8, "h": 8 },
    "duration": 100
   },
   {
    "filename": "particle-heart 1.aseprite",
    "frame": { "x": 8, "y": 0, "w": 8, "h": 8 },
    "rotated": false,
    "trimmed": false,
    "spriteSourceSize": { "x": 0, "y": 0, "w": 8, "h": 8 },
    "sourceSize": { "w": 8, "h": 8 },
    "duration": 100
   },
   {
    "filename": "particle-heart 2.aseprite",
    "frame": { "x": 16, "y": 0, "w": 8, "h": 8 },
    "rotated": false,
    "trimmed": false,
    "spriteSourceSize": { "x": 0, "y": 0, "w": 8, "h": 8 },
    "sourceSize": { "w": 8, "h": 8 },
    "duration": 100
   },
   {
    "filename": "particle-heart 3.aseprite",
    "frame": { "x": 24, "y": 0, "w": 8, "h": 8 },
    "rotated": false,
    "trimmed": false,
    "spriteSourceSize": { "x": 0, "y": 0, "w": 8, "h": 8 },
    "sourceSize": { "w": 8, "h": 8 },
    "duration": 100
   },
   {
    "filename": "particle-heart 4.aseprite",
    "frame": { "x": 32, "y": 0, "w": 8, "h": 8 },
    "rotated": false,
    "trimmed": false,
    "spriteSourceSize": { "x": 0, "y": 0, "w": 8, "h": 8 },
    "sourceSize": { "w": 8, "h": 8 },
    "duration": 100
   },
   {
    "filename": "particle-heart 5.aseprite",
    "frame": { "x": 40, "y": 0, "w": 8, "h": 8 },
    "rotated": false,
    "trimmed": false,
    "spriteSourceSize": { "x": 0, "y": 0, "w": 8, "h": 8 },
    "sourceSize": { "w": 8, "h": 8 },
    "duration": 100
   },
   {
    "filename": "particle-heart 6.aseprite",
    "frame": { "x": 48, "y": 0, "w": 8, "h": 8 },
    "rotated": false,
    "trimmed": false,
    "spriteSourceSize": { "x": 0, "y": 0, "w": 8, "h": 8 },
    "sourceSize": { "w": 8, "h": 8 },
    "duration": 100
   },
   {
    "filename": "particle-heart 7.aseprite",
    "frame": { "x": 56, "y": 0, "w": 8, "h": 8 },
    "rotated": false,
    "trimmed": false,
    "spriteSourceSize": { "x": 0, "y": 0, "w": 8, "h": 8 },
    "sourceSize": { "w": 8, "h": 8 },
    "duration": 100
   },
   {
    "filename": "particle-heart 8.aseprite",
    "frame": { "x": 64, "y": 0, "w": 8, "h": 8 },
    "rotated": false,
    "trimmed": false,
    "spriteSourceSize": { "x": 0, "y": 0, "w": 8, "h": 8 },
    "sourceSize": { "w": 8, "h": 8 },
    "duration": 100
   },
   {
    "filename": "particle-heart 9.aseprite",
    "frame": { "x": 72, "y": 0, "w": 8, "h": 8 },
    "rotated": false,
    "trimmed": false,
    "spriteSourceSize": { "x": 0, "y": 0, "w": 8, "h": 8 },
    "sourceSize": { "w": 8, "h": 8 },
    "duration": 100
   },
   {
    "filename": "particle-heart 10.aseprite",
    "frame": { "x": 80, "y": 0, "w": 8, "h": 8 },
    "rotated": false,
    "trimmed": false,
    "spriteSourceSize": { "x": 0, "y": 0, "w": 8, "h": 8 },
    "sourceSize": { "w": 8, "h": 8 },
    "duration": 100
   },
   {
    "filename": "particle-heart 11.aseprite",
    "frame": { "x": 88, "y": 0, "w": 8, "h": 8 },
    "rotated": false,
    "trimmed": false,
    "spriteSourceSize": { "x": 0, "y": 0, "w": 8, "h": 8 },
    "sourceSize": { "w": 8, "h": 8 },
    "duration": 100
   }
 ],
 "meta": {
  "app": "http://www.aseprite.org/",
  "version": "1.2.40-dev",
  "image": "particle-heart.png",
  "format": "I8",
  "size": { "w": 96, "h": 8 },
  "scale": "1"
 }
}
